msprior/__init__.py
msprior/attention.py
msprior/dataset.py
msprior/preprocessor.py
msprior/rwkv.py
msprior/scripted.py
msprior/task.py
msprior/utils.py
msprior/configs/decoder_only.gin
msprior/configs/flattened.gin
msprior/configs/modulated_alibi.gin
msprior/configs/recurrent.gin
msprior/configs/rwkv.gin
msprior/configs/rwkv_semantic.gin
msprior/cuda/wkv_cuda.cu
msprior/cuda/wkv_op.cpp
msprior_scripts/__init__.py
msprior_scripts/combine.py
msprior_scripts/compact.py
msprior_scripts/export.py
msprior_scripts/main_cli.py
msprior_scripts/preprocess.py
msprior_scripts/train.py
tests/__init__.py
tests/test_attention.py
tests/test_cache.py
tests/test_configs.py
acids_msprior-1.1.3.dist-info/METADATA
acids_msprior-1.1.3.dist-info/WHEEL
acids_msprior-1.1.3.dist-info/entry_points.txt
acids_msprior-1.1.3.dist-info/top_level.txt
acids_msprior-1.1.3.dist-info/RECORD
