Metadata-Version: 2.1
Name: acids-msprior
Version: 1.1.3
Summary: MSPRIOR: A multiscale prior model for realtime temporal learning
Author: Antoine CAILLON
Author-email: caillon@ircam.fr
Classifier: Programming Language :: Python :: 3
Classifier: License :: OSI Approved :: MIT License
Classifier: Operating System :: OS Independent
Requires-Python: >=3.9
Requires-Dist: absl-py
Requires-Dist: cached-conv
Requires-Dist: einops
Requires-Dist: gin-config
Requires-Dist: GPUtil
Requires-Dist: librosa
Requires-Dist: lmdb
Requires-Dist: nn-tilde
Requires-Dist: numpy
Requires-Dist: pathos
Requires-Dist: pytest
Requires-Dist: pytorch-lightning
Requires-Dist: torch
Requires-Dist: tqdm
Requires-Dist: udls
Requires-Dist: acids-rave
